typoglycemia/__init__.py
typoglycemia/__main__.py
typoglycemia/main.py
typoglycemia-0.1.1.dist-info/METADATA
typoglycemia-0.1.1.dist-info/WHEEL
typoglycemia-0.1.1.dist-info/entry_points.txt
typoglycemia-0.1.1.dist-info/RECORD
