Metadata-Version: 2.3
Name: typoglycemia
Version: 0.1.1
Summary: A Python package for scrambling the inner letters of words in a sentence while keeping the first and last letters in place.
Project-URL: Repository, https://github.com/hooli-dev/typoglycemia
Author-email: hooli-dev <t.hooli.jp@gmail.com>
Requires-Python: >=3.8
